wallpaper_setter/__init__.py
wallpaper_setter/add.py
wallpaper_setter/cli.py
wallpaper_setter/delete.py
wallpaper_setter/edit.py
wallpaper_setter/initialize.py
wallpaper_setter/lst.py
wallpaper_setter/set.py
wallpaper_setter/toggle.py
wallpaper_setter/update.py
wallpaper_setter/db/__init__.py
wallpaper_setter/db/connect.py
wallpaper_setter/db/models.py
wallpaper_setter/utils/__init__.py
wallpaper_setter/utils/config.py
wallpaper_setter/utils/db.py
wallpaper_setter/utils/table.py
wallpaper_setter/utils/wallpaper.py
wallpaper_setter-0.1.1.dist-info/LICENSE
wallpaper_setter-0.1.1.dist-info/METADATA
wallpaper_setter-0.1.1.dist-info/WHEEL
wallpaper_setter-0.1.1.dist-info/entry_points.txt
wallpaper_setter-0.1.1.dist-info/top_level.txt
wallpaper_setter-0.1.1.dist-info/RECORD
