Metadata-Version: 2.1
Name: wallpaper-setter
Version: 0.1.1
Summary: Simple utility for managing wallpapers from the command-line
Home-page: https://gitlab.com/dhoekstra/wallpaper-setter
Author: Douwe Hoekstra
Author-email: douwe.hoekstra2512@gmail.com
License: UNKNOWN
Keywords: wallpaper setter colors manager
Platform: UNKNOWN
Classifier: Environment :: Console
Classifier: Programming Language :: Python :: 3
Classifier: License :: OSI Approved :: GNU General Public License v3 (GPLv3)
Classifier: Operating System :: POSIX :: Linux
Requires-Python: >=3.7
Requires-Dist: click (>=7.1.1)
Requires-Dist: sqlalchemy (>=1.3.0)
Requires-Dist: toml (>=0.10.0)
Requires-Dist: pywal (>=3.3.0)
Requires-Dist: easy-table (>=0.0.4)
